django_middleware_global_request/__init__.py
django_middleware_global_request/admin.py
django_middleware_global_request/apps.py
django_middleware_global_request/middleware.py
django_middleware_global_request/models.py
django_middleware_global_request/tests.py
django_middleware_global_request/views.py
django_middleware_global_request/migrations/__init__.py
django_middleware_global_request-0.3.6.dist-info/licenses/LICENSE
django_middleware_global_request-0.3.6.dist-info/METADATA
django_middleware_global_request-0.3.6.dist-info/WHEEL
django_middleware_global_request-0.3.6.dist-info/top_level.txt
django_middleware_global_request-0.3.6.dist-info/RECORD
