Metadata-Version: 2.4
Name: django-middleware-global-request
Version: 0.3.6
Summary: Django middleware that keep request instance for every thread.
Author: rRR0VrFP
Maintainer: rRR0VrFP
License: MIT
Keywords: django extensions,django middleware global request
Classifier: Development Status :: 5 - Production/Stable
Classifier: Intended Audience :: Developers
Classifier: Topic :: Software Development :: Libraries :: Python Modules
Classifier: License :: OSI Approved :: MIT License
Classifier: Programming Language :: Python :: 3
Classifier: Programming Language :: Python :: 3 :: Only
Requires: django
License-File: LICENSE
Requires-Dist: django
Dynamic: author
Dynamic: classifier
Dynamic: description
Dynamic: description-content-type
Dynamic: keywords
Dynamic: license
Dynamic: license-file
Dynamic: maintainer
Dynamic: requires
Dynamic: requires-dist
Dynamic: summary
